iflow_mcp_leftspin_mcp_xcode_diagnostics-1.0.0.dist-info/licenses/LICENSE
xcode_diagnostics/__init__.py
xcode_diagnostics/__main__.py
xcode_diagnostics/xcode_diagnostics.py
iflow_mcp_leftspin_mcp_xcode_diagnostics-1.0.0.dist-info/METADATA
iflow_mcp_leftspin_mcp_xcode_diagnostics-1.0.0.dist-info/WHEEL
iflow_mcp_leftspin_mcp_xcode_diagnostics-1.0.0.dist-info/entry_points.txt
iflow_mcp_leftspin_mcp_xcode_diagnostics-1.0.0.dist-info/top_level.txt
iflow_mcp_leftspin_mcp_xcode_diagnostics-1.0.0.dist-info/RECORD
