Metadata-Version: 2.4
Name: iflow-mcp-leftspin-mcp-xcode-diagnostics
Version: 1.0.0
Summary: MCP plugin for extracting and viewing Xcode build errors and warnings
Home-page: https://github.com/leftspin/mcp-xcode-diagnostics
Author: Mike R. Manzano
Author-email: mike@clicketyclacks.co
Classifier: Programming Language :: Python :: 3
Classifier: License :: OSI Approved :: MIT License
Classifier: Operating System :: MacOS :: MacOS X
Classifier: Development Status :: 4 - Beta
Classifier: Intended Audience :: Developers
Classifier: Topic :: Software Development :: Build Tools
Requires-Python: >=3.6
License-File: LICENSE
Requires-Dist: mcp>=1.2.0; platform_system == "Darwin"
Dynamic: author
Dynamic: author-email
Dynamic: classifier
Dynamic: description
Dynamic: description-content-type
Dynamic: home-page
Dynamic: license-file
Dynamic: requires-dist
Dynamic: requires-python
Dynamic: summary
